{
    "success": true,
    "data": {
      "topicList": [{
          "id": 1,
          "title": " 故事会 ",
          "imgUrl": "https://upload.jianshu.io/collections/images/95/1.jpg?imageMogr2/auto-orient/strip|imageView2/1/w/64/h/64"
        },
        {
          "id": 2,
          "title": " 自然科普 ",
          "imgUrl": "https://upload.jianshu.io/collections/images/76/12.jpg?imageMogr2/auto-orient/strip|imageView2/1/w/64/h/64"
        },
        {
          "id": 3,
          "title": " 简书电影 ",
          "imgUrl": "https://upload.jianshu.io/collections/images/21/20120316041115481.jpg?imageMogr2/auto-orient/strip|imageView2/1/w/64/h/64"
        },
        {
          "id": 4,
          "title": " 摄影 ",
          "imgUrl": "https://upload.jianshu.io/collections/images/83/1.jpg?imageMogr2/auto-orient/strip|imageView2/1/w/64/h/64"
        },
        {
          "id": 5,
          "title": "@IT 互联网 ",
          "imgUrl": "https://upload.jianshu.io/collections/images/14/6249340_194140034135_2.jpg?imageMogr2/auto-orient/strip|imageView2/1/w/64/h/64"
        },
        {
          "id": 6,
          "title": " 手绘 ",
          "imgUrl": "https://upload.jianshu.io/collections/images/283250/%E6%BC%AB%E7%94%BB%E4%B8%93%E9%A2%98.jpg?imageMogr2/auto-orient/strip|imageView2/1/w/64/h/64"
        },
        {
          "id": 7,
          "title": " 读书 ",
          "imgUrl": "https://upload.jianshu.io/collections/images/4/sy_20091020135145113016.jpg?imageMogr2/auto-orient/strip|imageView2/1/w/64/h/64"
        }
      ],
      "articleList": [{
          "id":1,
          "title": " 江疏影中性风格写真曝光，长发飘飘也难掩霸气，网友：替胡歌可惜 ",
          "desc": " 导语：江疏影中性风格写真曝光，长发飘飘也难掩霸气，网友：替胡歌可惜 从致青春中被视为花瓶的阮莞到好先生中演技实力派的江莱，江疏影自出道以来一步步...",
          "author": "Aidress",
          "image": "//upload-images.jianshu.io/upload_images/3949843-8dd97ab6dce41735.jpg?imageMogr2/auto-orient/strip|imageView2/1/w/300/h/240"
        },
        {
          "id":2,
          "title": " 完结《洵珺天下》之后以及新文 ",
          "desc": " 历经千辛万苦，终于写了自己的第一部完结作品。虽然是一部同人文，但也算自己的处女作吧！ 首先非常感谢这段时间以来各位朋友们的支持，尤其是秋月醉、涅...",
          "author": " 锦歌长安 ",
          "image": "//upload-images.jianshu.io/upload_images/2920027-da482682cc76d1fc.png?imageMogr2/auto-orient/strip|imageView2/1/w/300/h/240"
        },
        {
          "id":3,
          "title": " 每天最重要的 2 小时：让自己成为高效的人 ",
          "desc": " 工作、加班、学习、运动、陪伴家人，当然还有娱乐，我们每天都被时间的脚步追赶着，每一刻都是忙碌的，而忙碌永远没有劲头。 当下，时间俨然已经成为最宝...",
          "author": " 爱吃的坦克 ",
          "image": "//upload-images.jianshu.io/upload_images/10746568-26f4733a3ad87c62.png?imageMogr2/auto-orient/strip|imageView2/1/w/300/h/240"
        },
        {
          "id":4,
          "title": " 小戏骨红楼梦：不是塑造明星，是打击明星 ",
          "desc": " 前段时间，一部剧中演员全部都是小孩子的《红楼梦》迅速走红，在网络上的口碑与声誉也是参差不齐。 有的人说，小孩子怎么能拍红楼梦？有的人则对剧中演员...",
          "author": " 孟水三千 ",
          "image": "//upload-images.jianshu.io/upload_images/12462768-204a4569985259c8.jpg?imageMogr2/auto-orient/strip|imageView2/1/w/300/h/240"
         
        },
        {
          "id":5,
          "title": "2018 上半年最好的 20 句文案！",
          "desc": " 关于增长 其实最容易的方式 就是简简单单的写几句 能够让你引起共鸣的文案 但是，通常 这也是最难的 精选了 20 句 2018 年上半年最好的那些文案...",
          "author": " 小明同学 swimming",
          "image": "//upload-images.jianshu.io/upload_images/530072-528ca6333b385d84?imageMogr2/auto-orient/strip|imageView2/1/w/300/h/240"
        },
        {
          "id":6,
          "title": " 摄影技巧｜为什么你拍的照片总是不清晰？",
          "desc": " 如果你发现你拍摄的照片很容易糊，很难拍摄出清晰的对焦照片，不要担心，下面九个设定可以帮助你在拍摄人的时候获得清晰的图像。 1 快门速度 如果你将快...",
          "author": "TonyG 国际芳香疗愈师 ",
          "image": "//upload-images.jianshu.io/upload_images/10748735-4276277c057670dd.jpg?imageMogr2/auto-orient/strip|imageView2/1/w/300/h/240"
        },
        {
          "id":7,
          "title": "《结构思考力》｜只有思考清晰，才能表达有力 ",
          "desc": " 之前我们分享了西村克己的《逻辑思考力》，学习如何培养以及进行逻辑思考。这次要分享的一本书是算得上是它的姊妹篇 —— 由李忠秋先生所著的《结构思考力》...",
          "author": " 非飞羽宇 ",
          "image": "//upload-images.jianshu.io/upload_images/11349740-d8eb36e1b54cdfc7?imageMogr2/auto-orient/strip|imageView2/1/w/300/h/240"
        },
        {
          "id":8,
          "title": " 我在使用的学习相关 App 推荐 ",
          "desc": " 受邀在知乎回答了一个问题：有什么好用的学习类 APP？以下是我的回复，供大家参考 —— 在回答中，我会先分享获取知识的 App；学了这些知识后，得用一...",
          "author": "PomoNote",
          "image": "//upload-images.jianshu.io/upload_images/9433599-aad2bd78c7553534.jpg?imageMogr2/auto-orient/strip|imageView2/1/w/300/h/240"
        },
        {
          "id":9,
          "title": " 三个月死磕 Python 是种怎样的体验？",
          "desc": "3 个月的死磕 Python 是种什么感觉？刚参加「 楼 + Python 实战・第 6 期 」的学员们告诉你答案，下面带来他们的真实评价。 作为实验...",
          "author": " 实验楼 ",
          "image": "//upload-images.jianshu.io/upload_images/226662-586f30791940a485.jpg?imageMogr2/auto-orient/strip|imageView2/1/w/300/h/240"
        },
        {
          "id":10,
          "title": " 素描入门 初学素描的你，素描排线方式正确吗？",
          "desc": " 素描桃桃来教你 ​ 练习排线，是学素描开始最初的阶段，也是画素描必经历的阶段，熟练地用线会使更容易的表现体积。练习排线，并...",
          "author": " 素描桃桃 ",
          "image": "//upload-images.jianshu.io/upload_images/9050915-0cf3a63d39949730?imageMogr2/auto-orient/strip|imageView2/1/w/300/h/240"
        },
        {
          "id":11,
          "title": " 设计师升职加薪必须知道的 10 个设计网站 ",
          "desc": " 设计行业经过几年的发展，已经进入到了相对成熟的时期。这无疑会对设计师有更高的要求和挑战。 随着 AI 的发展，设计甚至从有形的设计，转变为无形的设计...",
          "author": "Mockplus 摹客 ",
          "image": "//upload-images.jianshu.io/upload_images/7220494-725864be7ef6347b?imageMogr2/auto-orient/strip|imageView2/1/w/300/h/240"
        },
        {
          "id":12,
          "title": " 为什么 Python 4.0 会与 Python 3.0 不同？",
          "desc": " 不管我们如何希望 PHP 永远天下第一，亦或是 Java 永久无敌，更或者希望 C 语言永远是最好的语言。然而，笔者今天搜索百度指数得知，Python 的指数...",
          "author": " 菜鸟 Python",
          "image": "//upload-images.jianshu.io/upload_images/12684358-3837549a89e7c84b.png?imageMogr2/auto-orient/strip|imageView2/1/w/300/h/240"
        },
        {
          "id":13,
          "title": " 超级好喝又减脂的 4 大蔬菜汤，在不长肉的情况下最大限度满足你 ",
          "desc": " 这四道汤如果没有减脂需求的妹子们也都可以喝，清淡不油腻，非常适合夏天餐前餐后来一碗。 一、素高汤 准备食材：娃娃菜、香菇、白萝卜； 步骤： 1、...",
          "author": " 阮阮小厨 ",
          "image": "//upload-images.jianshu.io/upload_images/12195411-a040624a0d93b58d.jpg?imageMogr2/auto-orient/strip|imageView2/1/w/300/h/240"
        }
      ],
      "recommendList": [{
          "id": "1",
          "cover": "//raw.githubusercontent.com/Toxicfy/Jianshu-React/master/src/statics/image/Days.png"
        },
        {
          "id": "2",
          "cover": "//raw.githubusercontent.com/Toxicfy/Jianshu-React/master/src/statics/image/Months.png"
        },
        {
          "id": "3",
          "cover": "//raw.githubusercontent.com/Toxicfy/Jianshu-React/master/src/statics/image/Serialize.png"
        },
        {
          "id": "4",
          "cover": "//raw.githubusercontent.com/Toxicfy/Jianshu-React/master/src/statics/image/CopyRight.png"
        },
        {
          "id": "5",
          "cover": "//raw.githubusercontent.com/Toxicfy/Jianshu-React/master/src/statics/image/BigSchool.png"
        }
      ],
      "authorList":[
        {
            "id": 15656008,
            "nickname": "南乔小妹",
            "avatar_source": "http://upload.jianshu.io/users/upload_avatars/15656008/93c7d4b4-973a-4797-aae9-83c84ef88d4d.jpg",
            "total_likes_count": 130,
            "total_wordage": 18576
        },
        {
            "id": 7129103,
            "nickname": "我是三七呀",
            "avatar_source": "http://upload.jianshu.io/users/upload_avatars/7129103/2dad53cd-a670-494d-afed-b054ffba3c0a.jpg",
            "total_likes_count": 684,
            "total_wordage": 164407
        },
        {
            "id": 13663978,
            "nickname": "一棹碧涛",
            "avatar_source": "http://upload.jianshu.io/users/upload_avatars/13663978/281cd128-edf2-4aa4-bef0-80c0f99ac89e.jpg",
            "total_likes_count": 1613,
            "total_wordage": 110305
        },
        {
            "id": 15124196,
            "nickname": "龙颜_a279",
            "avatar_source": "http://upload.jianshu.io/users/upload_avatars/15124196/2d238ed4-6e77-40a0-8609-608988bef912",
            "total_likes_count": 2185,
            "total_wordage": 31789
        },
        {
            "id": 14499488,
            "nickname": "克东092周宇鹏",
            "avatar_source": "http://upload.jianshu.io/users/upload_avatars/14499488/d842fbd4-4d63-40ad-8db5-691dba850f19",
            "total_likes_count": 1166,
            "total_wordage": 173305
        },
        {
            "id": 10879359,
            "nickname": "邻家小娟子",
            "avatar_source": "http://upload.jianshu.io/users/upload_avatars/10879359/6091deea-564a-40e8-b4fa-f5bc56792ae3.jpg",
            "total_likes_count": 27,
            "total_wordage": 21002
        },
        {
            "id": 15384069,
            "nickname": "芳香四溢_b2ae",
            "avatar_source": "http://upload.jianshu.io/users/upload_avatars/15384069/9fb57d47-c55a-49f4-a012-e82efbe1658f",
            "total_likes_count": 181,
            "total_wordage": 38941
        },
        {
            "id": 9683339,
            "nickname": "宋云梅",
            "avatar_source": "http://upload.jianshu.io/users/upload_avatars/9683339/e41bc30b-49ee-410d-a8c3-4169ae4e0144.jpg",
            "total_likes_count": 1312,
            "total_wordage": 52070
        },
        {
            "id": 15848101,
            "nickname": "秋水语韵",
            "avatar_source": "http://upload.jianshu.io/users/upload_avatars/15848101/482e5630-4869-415b-87c9-db14a2927bde.jpg",
            "total_likes_count": 191,
            "total_wordage": 23310
        },
        {
            "id": 10870320,
            "nickname": "小狼XL",
            "avatar_source": "http://upload.jianshu.io/users/upload_avatars/10870320/ee6fce0f-eb81-413a-b64c-3868941b60c2.jpg",
            "total_likes_count": 153,
            "total_wordage": 27232
        },
        {
            "id": 8316803,
            "nickname": "晨曦话流萤",
            "avatar_source": "http://upload.jianshu.io/users/upload_avatars/8316803/e356ff0f-5672-4c95-907f-5b1de320ffd2.jpg",
            "total_likes_count": 372,
            "total_wordage": 39010
        },
        {
            "id": 13515354,
            "nickname": "金锦鲤",
            "avatar_source": "http://upload.jianshu.io/users/upload_avatars/13515354/b639afc8-acde-4a31-aee7-cb15e91fec85.jpg",
            "total_likes_count": 163,
            "total_wordage": 32920
        },
        {
            "id": 6966595,
            "nickname": "娜里风景独好",
            "avatar_source": "http://upload.jianshu.io/users/upload_avatars/6966595/b5c7218b-3692-48dc-91af-98a312b0d280",
            "total_likes_count": 80,
            "total_wordage": 96270
        },
        {
            "id": 14547546,
            "nickname": "诗梦江南",
            "avatar_source": "http://upload.jianshu.io/users/upload_avatars/14547546/16d35dec-7d23-47e1-bdae-e50cc4eb667d.jpg",
            "total_likes_count": 284,
            "total_wordage": 39798
        },
        {
            "id": 10511071,
            "nickname": "一直长大的小幸福",
            "avatar_source": "http://upload.jianshu.io/users/upload_avatars/10511071/fd2d4f0c-8cb6-4a8b-9375-6a9ae31efd7d",
            "total_likes_count": 58,
            "total_wordage": 20251
        },
        {
            "id": 14934729,
            "nickname": "秀火儒林",
            "avatar_source": "http://upload.jianshu.io/users/upload_avatars/14934729/8a7b51ab-47b2-4de7-991c-96e0b0950820.jpg",
            "total_likes_count": 593,
            "total_wordage": 34998
        },
        {
            "id": 11033898,
            "nickname": "李俊亚",
            "avatar_source": "http://upload.jianshu.io/users/upload_avatars/11033898/64125fa4-e2d6-46aa-a4a4-9262779badd0.jpg",
            "total_likes_count": 64,
            "total_wordage": 48112
        },
        {
            "id": 8830844,
            "nickname": "小矮人Plus",
            "avatar_source": "http://upload.jianshu.io/users/upload_avatars/8830844/1183ed8b-3bf7-4732-96db-b008a99668c5.jpg",
            "total_likes_count": 76,
            "total_wordage": 26159
        },
        {
            "id": 10929713,
            "nickname": "傅悦天",
            "avatar_source": "http://upload.jianshu.io/users/upload_avatars/10929713/ce1e6f3f-8a24-45f3-b627-f4d45411cbee.jpg",
            "total_likes_count": 416,
            "total_wordage": 74841
        },
        {
            "id": 2602969,
            "nickname": "鹿幼幼",
            "avatar_source": "http://upload.jianshu.io/users/upload_avatars/2602969/2222030b-251d-452a-90f3-df666ac9034a.jpg",
            "total_likes_count": 11844,
            "total_wordage": 306309
        }
    ]
    }
  }